LICENSE.txt
MANIFEST.in
README.rst
setup.cfg
setup.py
tiny_crash_reporter.egg-info/PKG-INFO
tiny_crash_reporter.egg-info/SOURCES.txt
tiny_crash_reporter.egg-info/dependency_links.txt
tiny_crash_reporter.egg-info/not-zip-safe
tiny_crash_reporter.egg-info/top_level.txt
tinycrashreporter/.DS_Store
tinycrashreporter/__init__.py
tinycrashreporter/__init__.pyc
tinycrashreporter/__pycache__/__init__.cpython-36.pyc
tinycrashreporter/samples/CrashyProgram.py
tinycrashreporter/samples/ImportedLibraryOnly.py
tinycrashreporter/tests/CrashTest.py